cerbos_sqlalchemy/__init__.py
cerbos_sqlalchemy/query.py
cerbos_sqlalchemy-0.3.2.dist-info/WHEEL
cerbos_sqlalchemy-0.3.2.dist-info/METADATA
cerbos_sqlalchemy-0.3.2.dist-info/RECORD
