Metadata-Version: 2.1
Name: cerbos-sqlalchemy
Version: 0.3.2
Summary: SQLAlchemy adapter for generating queries with Cerbos: an open core, language-agnostic, scalable authorization solution
License: Apache-2.0
Author-email: Cerbos Developers <sdk+sqlalchemy@cerbos.dev>
Requires-Python: >=3.8
Classifier: Development Status :: 4 - Beta
Classifier: Intended Audience :: Developers
Classifier: Topic :: Security
Classifier: Topic :: Software Development :: Libraries
Requires-Dist: cerbos>=0.10.4
Requires-Dist: sqlalchemy>=1.4
Provides-Extra: testcontainers
Requires-Dist: testcontainers>=3.5.3; extra == "testcontainers"
Project-URL: Homepage, https://cerbos.dev
Project-URL: Repository, https://github.com/cerbos/query-plan-adapters/tree/main/sqlalchemy
